{
 "ministry-of-electronics-it-meity": {
  "name": "Ministry of Electronics & IT (MeitY)",
  "url": "https://meity.gov.in/",
  "last_checked": "2026-07-17T19:30:50Z",
  "ok": true,
  "baseline_at": "2026-07-07T19:13:41Z",
  "last_change": "2026-07-17T14:00:01Z"
 },
 "ministry-of-information-broadcasting-mib": {
  "name": "Ministry of Information & Broadcasting (MIB)",
  "url": "https://mib.gov.in/",
  "last_checked": "2026-07-17T19:30:50Z",
  "ok": true,
  "baseline_at": "2026-07-07T19:13:41Z",
  "last_change": "2026-07-17T10:57:16Z"
 },
 "telecom-regulatory-authority-of-india-trai": {
  "name": "Telecom Regulatory Authority of India (TRAI)",
  "url": "https://www.trai.gov.in/",
  "last_checked": "2026-07-17T19:30:50Z",
  "ok": false,
  "baseline_at": "2026-07-07T19:13:41Z",
  "last_change": "2026-07-17T14:00:01Z",
  "error": "fetch failed after retries: HTTPSConnectionPool(host='www.trai.gov.in', port=443): Max retries exceeded with url: / (Caused by ConnectTimeoutError(<HTTPSConnection(host='www.trai.gov.in', port=443) at 0x7f3f2c0e2b10>, 'Connection to www.trai.gov.in timed out. (connect timeout=45)'))"
 },
 "department-of-telecommunications-dot": {
  "name": "Department of Telecommunications (DoT)",
  "url": "https://dot.gov.in/",
  "last_checked": "2026-07-17T19:30:50Z",
  "ok": true,
  "baseline_at": "2026-07-07T19:13:41Z",
  "last_change": "2026-07-17T08:25:54Z"
 }
}